decto/__init__.py
decto/predict.py
decto/train.py
decto/dataset/DefaultDataset.py
decto/dataset/VIADataset.py
decto/dataset/VOCDataset.py
decto/dataset/__init__.py
decto/dataset/augmentation.py
decto/dataset/loader.py
decto/dataset/preprocess.py
decto/model/__init__.py
decto/model/backbone.py
decto/model/faster_rcnn.py
decto/model/fpn.py
decto/model/pooler.py
decto/model/predictor.py
decto/model/roihead.py
decto/model/rpn.py
decto/model/trainer.py
decto/utils/__init__.py
decto/utils/anchor.py
decto/utils/box.py
decto/utils/config.py
decto/utils/download_model.py
decto/utils/initialize.py
decto/utils/logger.py
decto/utils/lr_decay.py
decto/utils/metrics.py
decto/utils/visualize.py
decto-0.1.2.dist-info/LICENSE
decto-0.1.2.dist-info/METADATA
decto-0.1.2.dist-info/WHEEL
decto-0.1.2.dist-info/top_level.txt
decto-0.1.2.dist-info/RECORD
