Metadata-Version: 2.1
Name: decto
Version: 0.1.2
Summary: Implement FasterRCNN using Feature Pyramid Network for Object Detection
Home-page: https://github.com/pbcquoc/decto
Author: pbcquoc
Author-email: pbcquoc@gmail.com
License: UNKNOWN
Platform: UNKNOWN
Classifier: Programming Language :: Python :: 3
Classifier: License :: OSI Approved :: MIT License
Classifier: Operating System :: OS Independent
Requires-Python: >=3.6
License-File: LICENSE
Requires-Dist: gdown (==3.11.0)
